odoo/addons/account_avatax_repair_oca/README.rst
odoo/addons/account_avatax_repair_oca/__init__.py
odoo/addons/account_avatax_repair_oca/__manifest__.py
odoo/addons/account_avatax_repair_oca/i18n/account_avatax_repair_oca.pot
odoo/addons/account_avatax_repair_oca/i18n/it.po
odoo/addons/account_avatax_repair_oca/models/__init__.py
odoo/addons/account_avatax_repair_oca/models/account_move.py
odoo/addons/account_avatax_repair_oca/models/avalara_salestax.py
odoo/addons/account_avatax_repair_oca/models/partner.py
odoo/addons/account_avatax_repair_oca/models/repair_fee.py
odoo/addons/account_avatax_repair_oca/models/repair_line.py
odoo/addons/account_avatax_repair_oca/models/repair_order.py
odoo/addons/account_avatax_repair_oca/readme/CONTRIBUTORS.rst
odoo/addons/account_avatax_repair_oca/readme/DESCRIPTION.rst
odoo/addons/account_avatax_repair_oca/readme/USAGE.rst
odoo/addons/account_avatax_repair_oca/static/description/icon.png
odoo/addons/account_avatax_repair_oca/static/description/index.html
odoo/addons/account_avatax_repair_oca/tests/__init__.py
odoo/addons/account_avatax_repair_oca/tests/test_repair_order.py
odoo/addons/account_avatax_repair_oca/views/avalara_salestax_view.xml
odoo/addons/account_avatax_repair_oca/views/partner_view.xml
odoo/addons/account_avatax_repair_oca/views/repair_order_view.xml
odoo_addon_account_avatax_repair_oca-16.0.1.0.0.4.dist-info/METADATA
odoo_addon_account_avatax_repair_oca-16.0.1.0.0.4.dist-info/WHEEL
odoo_addon_account_avatax_repair_oca-16.0.1.0.0.4.dist-info/top_level.txt
odoo_addon_account_avatax_repair_oca-16.0.1.0.0.4.dist-info/RECORD
