Metadata-Version: 2.1
Name: odoo-addon-account_avatax_repair_oca
Version: 16.0.1.0.0.4
Requires-Python: >=3.10
Requires-Dist: odoo-addon-account_avatax_oca>=16.0dev,<16.1dev
Requires-Dist: odoo>=16.0a,<16.1dev
Summary: Repair Orders with automatic Tax application using Avatax
Home-page: https://github.com/OCA/account-fiscal-rule
License: AGPL-3
Author: ForgeFlow, Odoo Community Association (OCA)
Author-email: support@odoo-community.org
Classifier: Programming Language :: Python
Classifier: Framework :: Odoo
Classifier: Framework :: Odoo :: 16.0
Classifier: License :: OSI Approved :: GNU Affero General Public License v3
